fdfs_client/__init__.py
fdfs_client/client.py
fdfs_client/connection.py
fdfs_client/exceptions.py
fdfs_client/fdfs_protol.py
fdfs_client/fdfs_test.py
fdfs_client/storage_client.py
fdfs_client/tracker_client.py
fdfs_client/utils.py
fastdfs_client_py3-1.0.0.dist-info/LICENSE
fastdfs_client_py3-1.0.0.dist-info/METADATA
fastdfs_client_py3-1.0.0.dist-info/WHEEL
fastdfs_client_py3-1.0.0.dist-info/top_level.txt
fastdfs_client_py3-1.0.0.dist-info/RECORD
