Metadata-Version: 2.1
Name: fastdfs-client-py3
Version: 1.0.0
Summary: Python3 and Python2 client for Fastdfs
Home-page: UNKNOWN
Author: Huanglg
Author-email: huanglg0425@gmail.com
License: GPLV3
Keywords: Fastdfs,Distribute File System
Platform: UNKNOWN
